prismio/__init__.py
prismio/main.py
prismio/rednerer.py
prismio-0.0.7.dist-info/LICENSE
prismio-0.0.7.dist-info/METADATA
prismio-0.0.7.dist-info/WHEEL
prismio-0.0.7.dist-info/entry_points.txt
prismio-0.0.7.dist-info/top_level.txt
prismio-0.0.7.dist-info/RECORD
