Metadata-Version: 2.1
Name: prismio
Version: 0.0.7
Summary: For now just for testing
Author: Parsa
Author-email: mehr2.business@example.com
Classifier: Programming Language :: Python :: 3
Classifier: License :: OSI Approved :: MIT License
Classifier: Operating System :: OS Independent
Requires-Python: >=3.6
License-File: LICENSE
Requires-Dist: flask
Requires-Dist: colorama
Requires-Dist: zenora
Requires-Dist: customtkinter
Requires-Dist: tqdm
Requires-Dist: alive-progress
Requires-Dist: moviepy
Requires-Dist: rabity
Requires-Dist: keyboard
